CHANGELOG.txt
LICENCE.txt
MANIFEST.in
README.txt
setup.py
charchittime/__init__.py
charhitcalcu.egg-info/PKG-INFO
charhitcalcu.egg-info/SOURCES.txt
charhitcalcu.egg-info/dependency_links.txt
charhitcalcu.egg-info/top_level.txt